frenetix_occlusion/__init__.py
frenetix_occlusion/agent.py
frenetix_occlusion/config/config.yaml
frenetix_occlusion/config/harm_params.json
frenetix_occlusion/config/risk_params.json
frenetix_occlusion/interface.py
frenetix_occlusion/metrics/__init__.py
frenetix_occlusion/metrics/be.py
frenetix_occlusion/metrics/cp.py
frenetix_occlusion/metrics/dce.py
frenetix_occlusion/metrics/hr.py
frenetix_occlusion/metrics/metric.py
frenetix_occlusion/metrics/ttc.py
frenetix_occlusion/metrics/ttce.py
frenetix_occlusion/metrics/utils/__init__.py
frenetix_occlusion/metrics/utils/collision_probability.py
frenetix_occlusion/metrics/utils/convert_dynamic_obstacle.py
frenetix_occlusion/metrics/utils/harm_model.py
frenetix_occlusion/metrics/utils/logistic_regression.py
frenetix_occlusion/metrics/wttc.py
frenetix_occlusion/route_planner.py
frenetix_occlusion/sensor_model.py
frenetix_occlusion/spawn_locator.py
frenetix_occlusion/utils/__init__.py
frenetix_occlusion/utils/fo_obstacle.py
frenetix_occlusion/utils/frenetix_handler.py
frenetix_occlusion/utils/helper_functions.py
frenetix_occlusion/utils/prediction_visualization.py
frenetix_occlusion/utils/sampling.py
frenetix_occlusion/utils/visualization.py
frenetix_occlusion-2024.1.3.dist-info/LICENSE
frenetix_occlusion-2024.1.3.dist-info/METADATA
frenetix_occlusion-2024.1.3.dist-info/WHEEL
frenetix_occlusion-2024.1.3.dist-info/entry_points.txt
frenetix_occlusion-2024.1.3.dist-info/RECORD
