Metadata-Version: 2.1
Name: frenetix-occlusion
Version: 2024.1.3
Summary: Frenetix Occlusion-aware Trajectory Validation Framework
License: LGPL-3.0-or-later
Author: Korbinian Moller
Author-email: korbinian.moller@tum.de
Maintainer: Korbinian Moller
Maintainer-email: korbinian.moller@tum.de
Requires-Python: >=3.9,<3.12
Classifier: License :: OSI Approved :: GNU Lesser General Public License v3 or later (LGPLv3+)
Classifier: Programming Language :: Python :: 3
Classifier: Programming Language :: Python :: 3.9
Classifier: Programming Language :: Python :: 3.10
Classifier: Programming Language :: Python :: 3.11
Requires-Dist: commonroad-drivability-checker (>=2023.1,<2024.0)
Requires-Dist: commonroad-io (>=2023.2,<2024.0)
Requires-Dist: commonroad-route-planner (>=2022.3,<2023.0)
Requires-Dist: numpy (>=1.24.2,<2.0.0)
Requires-Dist: shapely (>=2.0.2,<3.0.0)
